Workbook

Sheet Category-POI
A1: KATEGORIA | B1: LICZBA | C1: WAGA | D1: Opis
A2: historic=memorial | B2: 153 | C2: 0.1 | D2: Miejsce pamięci (pomnik upamiętniający osobę/wydarzenie, tablica pamiątkowa, głaz pamięci – zazwyczaj mniejsze obiekty).
A3: tourism=artwork | B3: 59 | C3: 0.02 | D3: Dzieło sztuki w przestrzeni publicznej (rzeźba, instalacja artystyczna, mural).
A4: natural=cave_entrance | B4: 37 | C4: 0.03 | D4: Wejście do jaskini.
A5: natural=peak | B5: 32 | C5: 0.15 | D5: Szczyt górski lub wzniesienie.
A6: tourism=viewpoint | B6: 26 | C6: 0.1 | D6: Punkt widokowy (miejsce, z którego rozciąga się ładna panorama).
A7: historic=monument | B7: 20 | C7: 0.2 | D7: Pomnik o dużej skali (np. Kolumna Zygmunta, Statua Wolności) lub obiekt o statusie pomnika historii.
A8: tourism=museum | B8: 20 | C8: 0.3 | D8: Muzeum
A9: tourism=attraction | B9: 16 | C9: 0.1 | D9: Atrakcja turystyczna (ogólny tag dla miejsc, które warto odwiedzić, często łączony z innymi).
A10: amenity=theatre | B10: 6 | C10: 0.3 | D10: Teatr (budynek lub scena plenerowa, gdzie odbywają się sztuki).
A11: leisure=nature_reserve | B11: 6 | C11: 0.3 | D11: Rezerwat przyrody (obszar prawnie chroniony).
A12: leisure=stadium | B12: 5 | C12: 0.3 | D12: Stadion (duży obiekt sportowy z trybunami dla widzów).
A13: historic=ruins | B13: 4 | C13: 0.15 | D13: Ruiny (pozostałości po dawnych budynkach, zamkach itp.).
... A17: tourism=gallery | B17: 2 | C17: 0.2 | D17: Galeria sztuki (miejsce, gdzie wystawia się obrazy/rzeźby, często komercyjne).
A18: RAZEM | B18: =SUM(B2:B17) -> 395
A22: PRZED FILTREM:
A23: KATEGORIA | B23: LICZBA | D23: Opis
A24: leisure=garden | B24: 752 | D24: Ogród (zaaranżowana przestrzeń zielona, np. ogród botaniczny, różanka, ogród japoński).
A25: leisure=playground | B25: 314 | D25: Plac zabaw dla dzieci.
A26: leisure=pitch | B26: 239 | D26: Boisko sportowe (do piłki nożnej, koszykówki, tenisa itp.).
A27: historic=memorial | B27: 153 | D27: Miejsce pamięci (pomnik upamiętniający osobę/wydarzenie, tablica pamiątkowa, głaz pamięci – zazwyczaj mniejsze obiekty).
A28: amenity=fountain | B28: 72 | D28: Źródło wody pitnej
A29: historic=wayside_shrine | B29: 63 | D29: Kapliczka przydrożna (bardzo popularne w Polsce małe obiekty sakralne przy drogach).
A30: tourism=artwork | B30: 59 | D30: Dzieło sztuki w przestrzeni publicznej (rzeźba, instalacja artystyczna, mural).
A31: amenity=place_of_worship | B31: 47 | D31: Miejsce kultu religijnego (kościół, cerkiew, meczet, synagoga, świątynia).
A32: leisure=park | B32: 41 | D32: Park (miejski, ogólnodostępny teren zielony z alejkami i ławkami).
A33: natural=cave_entrance | B33: 37 | D33: Wejście do jaskini.
A34: natural=peak | B34: 32 | D34: Szczyt górski lub wzniesienie.
A35: tourism=viewpoint | B35: 26 | D35: Punkt widokowy (miejsce, z którego rozciąga się ładna panorama).
... A45: tourism=gallery | B45: 2 | D45: Galeria sztuki (miejsce, gdzie wystawia się obrazy/rzeźby, często komercyjne).
B46: =SUM(B24:B45) -> 1919

Sheet POI
A1: name | B1: category | C1: lat | D1: lon | E1: classification;; | H1: WAGA
A2: Kielecki Teatr Tańca | B2: amenity=theatre | C2: 50.868425 | D2: 20.63764 | E2: kulturowa; eventowa; | H2: =VLOOKUP(B2, 'Category-POI'!$A$2:$C$17,3,FALSE) -> 0.3
A3: Muszla koncertowa | B3: amenity=theatre | C3: 50.868183 | D3: 20.625077 | E3: kulturowa; eventowa; | H3: 0.2
A4: Filharmonia Świętokrzyska im. Oskara Kolberga | B4: amenity=theatre | C4: 50.866618 | D4: 20.635938 | E4: kulturowa; eventowa; | H4: =VLOOKUP(B4, 'Category-POI'!$A$2:$C$17,3,FALSE) -> 0.3
A5: Amfiteatr Kadzielnia im. Andrzeja Litwina | B5: amenity=theatre | C5: 50.859816 | D5: 20.618565 | E5: kulturowa; eventowa; | H5: =VLOOKUP(B5, 'Category-POI'!$A$2:$C$17,3,FALSE) -> 0.3
A6: Teatr Dramatyczny im. Stefana Żeromskiego | B6: amenity=theatre | C6: 50.871103 | D6: 20.628886 | E6: kulturowa; eventowa; | H6: =VLOOKUP(B6, 'Category-POI'!$A$2:$C$17,3,FALSE) -> 0.3
A7: Teatr Lalki i Aktora "Kubuś" im. Stefana Karskiego | B7: amenity=theatre | C7: 50.868057 | D7: 20.627559 | E7: kulturowa; eventowa; | H7: =VLOOKUP(B7, 'Category-POI'!$A$2:$C$17,3,FALSE) -> 0.3
A8: Pałac Biskupów Krakowskich | B8: historic=castle | C8: 50.869213 | D8: 20.627673 | E8: edukacyjna;; | H8: =VLOOKUP(B8, 'Category-POI'!$A$2:$C$17,3,FALSE) -> 0.4
A9: Pałacyk Honigmana | B9: historic=castle | C9: 50.869646 | D9: 20.636495 | E9: edukacyjna;; | H9: =VLOOKUP(B9, 'Category-POI'!$A$2:$C$17,3,FALSE) -> 0.4
A10: Bohaterom Walk o Niepodległość | B10: historic=memorial | C10: 50.855185 | D10: 20.622981 | E10: edukacyjna; kulturowa; | H10: =VLOOKUP(B10, 'Category-POI'!$A$2:$C$17,3,FALSE) -> 0.1
A11: Pamięci Żołnierzy Legionów Polskich 1914 r. | B11: historic=memorial | C11: 50.884308 | D11: 20.641591 | E11: edukacyjna; kulturowa; | H11: =VLOOKUP(B11, 'Category-POI'!$A$2:$C$17,3,FALSE) -> 0.1
A12: Pomnik Czynu Legionowego | B12: historic=memorial | C12: 50.864109 | D12: 20.627187 | E12: edukacyjna; kulturowa; | H12: =VLOOKUP(B12, 'Category-POI'!$A$2:$C$17,3,FALSE) -> 0.1
A13: Pomnik Niepodległości | B13: historic=memorial | C13: 50.873966 | D13: 20.618675 | E13: edukacyjna; kulturowa; | H13: =VLOOKUP(B13, 'Category-POI'!$A$2:$C$17,3,FALSE) -> 0.1
A14: Pomnik Strażaków | B14: historic=memorial | C14: 50.870707 | D14: 20.647533 | E14: edukacyjna; kulturowa; | H14: =VLOOKUP(B14, 'Category-POI'!$A$2:$C$17,3,FALSE) -> 0.1
A15: Most im. kpt. Kazimierza Herwina Piątka | B15: historic=memorial | C15: 50.832839 | D15: 20.53623 | E15: edukacyjna; kulturowa; | H15: =VLOOKUP(B15, 'Category-POI'!$A$2:$C$17,3,FALSE) -> 0.1
... A161: Pomnik poświecony Zygmuntowi Firleyowi "Kajtkowi" | B161: historic=memorial | C161: 50.841674 | D161: 20.538446 | E161: edukacyjna; kulturowa; | H161: =VLOOKUP(B161, 'Category-POI'!$A$2:$C$17,3,FALSE) -> 0.1
A162: Naszym Poprzednikom, którzy dbali o lasy | B162: historic=memorial | C162: 50.896531 | D162: 20.608371 | H162: =VLOOKUP(B162, 'Category-POI'!$A$2:$C$17,3,FALSE) -> 0.1
A163: Pomnik Armii Krajowej | B163: historic=monument | C163: 50.868279 | D163: 20.630702 | E163: edukacyjna; kulturowa; | H163: =VLOOKUP(B163, 'Category-POI'!$A$2:$C$17,3,FALSE) -> 0.2
A164: Pomnik Fryderyka Chopina | B164: historic=monument | C164: 50.869103 | D164: 20.625233 | E164: edukacyjna; kulturowa; | H164: =VLOOKUP(B164, 'Category-POI'!$A$2:$C$17,3,FALSE) -> 0.2
A165: Pomnik Henryka Sienkiewicza | B165: historic=monument | C165: 50.868594 | D165: 20.635943 | E165: edukacyjna; kulturowa; | H165: =VLOOKUP(B165, 'Category-POI'!$A$2:$C$17,3,FALSE) -> 0.2
A166: Pomnik Jana Pawła II | B166: historic=monument | C166: 50.86832 | D166: 20.628698 | E166: edukacyjna; kulturowa; | H166: =VLOOKUP(B166, 'Category-POI'!$A$2:$C$17,3,FALSE) -> 0.2
A167: Pomnik Stanisława Staszica | B167: historic=monument | C167: 50.866982 | D167: 20.626929 | E167: edukacyjna; kulturowa; | H167: =VLOOKUP(B167, 'Category-POI'!$A$2:$C$17,3,FALSE) -> 0.2
A168: Homo Homini | B168: historic=monument | C168: 50.855952 | D168: 20.624942 | E168: edukacyjna; kulturowa; | H168: =VLOOKUP(B168, 'Category-POI'!$A$2:$C$17,3,FALSE) -> 0.2
A169: Harcerzom poległym za ojczyznę | B169: historic=monument | C169: 50.866868 | D169: 20.621691 | E169: edukacyjna; kulturowa; | H169: =VLOOKUP(B169, 'Category-POI'!$A$2:$C$17,3,FALSE) -> 0.2
A170: Pomnik świętego Jana Pawła II | B170: historic=monument | C170: 50.874511 | D170: 20.611722 | E170: edukacyjna; kulturowa; | H170: =VLOOKUP(B170, 'Category-POI'!$A$2:$C$17,3,FALSE) -> 0.2
A171: Pomnik Bojowników o Wyzwolenie Narodowe i Społeczne | B171: historic=monument | C171: 50.859506 | D171: 20.617068 | E171: edukacyjna; kulturowa; | H171: =VLOOKUP(B171, 'Category-POI'!$A$2:$C$17,3,FALSE) -> 0.2
A172: Pomnik Józefa Piłsudskiego | B172: historic=monument | C172: 50.867327 | D172: 20.634587 | E172: edukacyjna; kulturowa; | H172: =VLOOKUP(B172, 'Category-POI'!$A$2:$C$17,3,FALSE) -> 0.2
A173: Tablica Tadeusza Kościuszki | B173: historic=monument | C173: 50.869934 | D173: 20.628091 | E173: edukacyjna; kulturowa; | H173: =VLOOKUP(B173, 'Category-POI'!$A$2:$C$17,3,FALSE) -> 0.2
A174: Pomnik Jana Nepomucena | B174: historic=monument | C174: 50.868568 | D174: 20.622916 | E174: edukacyjna; kulturowa; | H174: =VLOOKUP(B174, 'Category-POI'!$A$2:$C$17,3,FALSE) -> 0.2
... A233: Jaskinia pod Fałdem / G-1.32 | B233: natural=cave_entrance | C233: 50.886955 | D233: 20.588344 | E233: edukacyjna; wypoczynkowa; | H233: =VLOOKUP(B233, 'Category-POI'!$A$2:$C$17,3,FALSE) -> 0.03
A234: Schronisko z Koralami, w Rafie | B234: natural=cave_entrance | C234: 50.862222 | D234: 20.617222 | H234: =VLOOKUP(B234, 'Category-POI'!$A$2:$C$17,3,FALSE) -> 0.03
A235: Karczówka | B235: natural=peak | C235: 50.867959 | D235: 20.58785 | E235: wypoczynkowa; sportowa; | H235: =VLOOKUP(B235, 'Category-POI'!$A$2:$C$17,3,FALSE) -> 0.15
A236: Dalnia | B236: natural=peak | C236: 50.872607 | D236: 20.582623 | E236: wypoczynkowa; sportowa; | H236: =VLOOKUP(B236, 'Category-POI'!$A$2:$C$17,3,FALSE) -> 0.15
A237: Grabina | B237: natural=peak | C237: 50.872224 | D237: 20.573888 | E237: wypoczynkowa; sportowa; | H237: =VLOOKUP(B237, 'Category-POI'!$A$2:$C$17,3,FALSE) -> 0.15
A238: Kadzielnia | B238: natural=peak | C238: 50.861161 | D238: 20.616717 | E238: wypoczynkowa; sportowa; | H238: =VLOOKUP(B238, 'Category-POI'!$A$2:$C$17,3,FALSE) -> 0.15
A239: Stokowa | B239: natural=peak | C239: 50.863964 | D239: 20.54966 | E239: wypoczynkowa; sportowa; | H239: =VLOOKUP(B239, 'Category-POI'!$A$2:$C$17,3,FALSE) -> 0.15
A240: Brusznia | B240: natural=peak | C240: 50.865355 | D240: 20.563586 | E240: wypoczynkowa; sportowa; | H240: =VLOOKUP(B240, 'Category-POI'!$A$2:$C$17,3,FALSE) -> 0.15
A241: Górki Czarnowskie | B241: natural=peak | C241: 50.881371 | D241: 20.606686 | E241: wypoczynkowa; sportowa; | H241: =VLOOKUP(B241, 'Category-POI'!$A$2:$C$17,3,FALSE) -> 0.15
A242: Słoneczna (Psia Górka) | B242: natural=peak | C242: 50.858497 | D242: 20.632683 | E242: wypoczynkowa; sportowa; | H242: =VLOOKUP(B242, 'Category-POI'!$A$2:$C$17,3,FALSE) -> 0.15
A243: Telegraf | B243: natural=peak | C243: 50.838218 | D243: 20.642816 | E243: wypoczynkowa; sportowa; | H243: =VLOOKUP(B243, 'Category-POI'!$A$2:$C$17,3,FALSE) -> 0.15
A244: Hałasa | B244: natural=peak | C244: 50.837872 | D244: 20.634384 | E244: wypoczynkowa; sportowa; | H244: =VLOOKUP(B244, 'Category-POI'!$A$2:$C$17,3,FALSE) -> 0.15
A245: Dymińska | B245: natural=peak | C245: 50.833055 | D245: 20.640962 | E245: wypoczynkowa; sportowa; | H245: =VLOOKUP(B245, 'Category-POI'!$A$2:$C$17,3,FALSE) -> 0.15
A246: Buk | B246: natural=peak | C246: 50.903071 | D246: 20.60792 | E246: wypoczynkowa; sportowa; | H246: =VLOOKUP(B246, 'Category-POI'!$A$2:$C$17,3,FALSE) -> 0.15
... A396: Wojewódzki Dom Kultury | B396: amenity=arts_centre | C396: 50.86324 | D396: 20.627049 | E396: kulturowa;; | H396: =VLOOKUP(B396, 'Category-POI'!$A$2:$C$17,3,FALSE) -> 0.01

Sheet Category-INF
A1: KATEGORIA | B1: LICZBA | C1: WAGA
A2: amenity=restaurant | B2: 146 | C2: 0.1
A3: amenity=fast_food | B3: 130 | C3: 0.03
A4: amenity=cafe | B4: 45 | C4: 0.05
A5: tourism=information | B5: 101 | C5: 0
A6: tourism=hotel | B6: 30 | C6: 0.2
A7: tourism=guest_house | B7: 6 | C7: 0.08
A8: tourism=hostel | B8: 6 | C8: 0.08
A9: tourism=apartment | B9: 1 | C9: 0.2
A10: tourism=motel | B10: 1 | C10: 0.08
A11: amenity=fountain | B11: 72 | C11: 0.01
A12: amenity=cinema | B12: 4 | C12: 0.1
A13: tourism=picnic_site | B13: 1 | C13: 0.1
A14: tourism=chalet | B14: 1 | C14: 0.01

Sheet INF
A1: name | B1: category | C1: lat | D1: lon | E1: classification;; | G1: Weight
A2: Zajazd Dyminy | B2: amenity=restaurant | C2: 50.801699 | D2: 20.619699 | E2: infrastruktura;; | G2: =VLOOKUP(B2,'Category-INF'!$A$2:$C$14,3,FALSE) -> 0.1
A3: Hotel Dyminy | B3: tourism=hotel | C3: 50.801813 | D3: 20.619573 | E3: infrastruktura;; | G3: =VLOOKUP(B3,'Category-INF'!$A$2:$C$14,3,FALSE) -> 0.2
A4: Trattoria Romana | B4: amenity=restaurant | C4: 50.805954 | D4: 20.620185 | E4: infrastruktura;; | G4: =VLOOKUP(B4,'Category-INF'!$A$2:$C$14,3,FALSE) -> 0.1
A5: Restauracja TELEGRAF | B5: amenity=restaurant | C5: 50.806092 | D5: 20.620199 | E5: infrastruktura;; | G5: =VLOOKUP(B5,'Category-INF'!$A$2:$C$14,3,FALSE) -> 0.1
A6: McDonald's | B6: amenity=fast_food | C6: 50.807877 | D6: 20.622315 | E6: infrastruktura;; | G6: =VLOOKUP(B6,'Category-INF'!$A$2:$C$14,3,FALSE) -> 0.03
A7: Capri | B7: amenity=restaurant | C7: 50.812347 | D7: 20.5543 | E7: infrastruktura;; | G7: =VLOOKUP(B7,'Category-INF'!$A$2:$C$14,3,FALSE) -> 0.1
A8: Ustronie leśne | B8: amenity=restaurant | C8: 50.821897 | D8: 20.620856 | E8: infrastruktura;; | G8: =VLOOKUP(B8,'Category-INF'!$A$2:$C$14,3,FALSE) -> 0.1
A9: Brak nazwy | B9: tourism=information | C9: 50.832534 | D9: 20.535813 | E9: infrastruktura;; | G9: =VLOOKUP(B9,'Category-INF'!$A$2:$C$14,3,FALSE) -> 0
A10: Brak nazwy | B10: tourism=information | C10: 50.832561 | D10: 20.535805 | E10: infrastruktura;; | G10: =VLOOKUP(B10,'Category-INF'!$A$2:$C$14,3,FALSE) -> 0
A11: Hotel "Stella" | B11: tourism=hotel | C11: 50.833508 | D11: 20.535946 | E11: infrastruktura;; | G11: =VLOOKUP(B11,'Category-INF'!$A$2:$C$14,3,FALSE) -> 0.2
A12: Na wypasie SmashBurger & Pizza | B12: amenity=fast_food | C12: 50.838504 | D12: 20.658749 | E12: infrastruktura;; | G12: =VLOOKUP(B12,'Category-INF'!$A$2:$C$14,3,FALSE) -> 0.03
A13: Kebab Zaitun | B13: amenity=fast_food | C13: 50.838786 | D13: 20.658509 | E13: infrastruktura;; | G13: =VLOOKUP(B13,'Category-INF'!$A$2:$C$14,3,FALSE) -> 0.03
A14: 365 | B14: tourism=hotel | C14: 50.841876 | D14: 20.605265 | E14: infrastruktura;; | G14: =VLOOKUP(B14,'Category-INF'!$A$2:$C$14,3,FALSE) -> 0.2
A15: Brak nazwy | B15: tourism=information | C15: 50.841893 | D15: 20.641414 | E15: infrastruktura;; | G15: =VLOOKUP(B15,'Category-INF'!$A$2:$C$14,3,FALSE) -> 0
A16: Brak nazwy | B16: tourism=information | C16: 50.841912 | D16: 20.640827 | E16: infrastruktura;; | G16: =VLOOKUP(B16,'Category-INF'!$A$2:$C$14,3,FALSE) -> 0
A17: Brak nazwy | B17: tourism=information | C17: 50.841939 | D17: 20.641419 | E17: infrastruktura;; | G17: =VLOOKUP(B17,'Category-INF'!$A$2:$C$14,3,FALSE) -> 0
A18: Siedem Pokus | B18: amenity=restaurant | C18: 50.841997 | D18: 20.60494 | E18: infrastruktura;; | G18: =VLOOKUP(B18,'Category-INF'!$A$2:$C$14,3,FALSE) -> 0.1
A19: Karczma Telegraf | B19: amenity=restaurant | C19: 50.84206 | D19: 20.641909 | E19: infrastruktura;; | G19: =VLOOKUP(B19,'Category-INF'!$A$2:$C$14,3,FALSE) -> 0.1
A20: Ceprówka | B20: amenity=fast_food | C20: 50.842086 | D20: 20.604374 | E20: infrastruktura;; | G20: =VLOOKUP(B20,'Category-INF'!$A$2:$C$14,3,FALSE) -> 0.03
A21: Pizzaliana | B21: amenity=fast_food | C21: 50.84383 | D21: 20.547244 | E21: infrastruktura;; | G21: =VLOOKUP(B21,'Category-INF'!$A$2:$C$14,3,FALSE) -> 0.03
A22: Brak nazwy | B22: tourism=chalet | C22: 50.844215 | D22: 20.532277 | E22: infrastruktura;; | G22: =VLOOKUP(B22,'Category-INF'!$A$2:$C$14,3,FALSE) -> 0.01
A23: Piekarnia Pod Telegrafem | B23: amenity=fast_food | C23: 50.844532 | D23: 20.648889 | E23: infrastruktura;; | G23: =VLOOKUP(B23,'Category-INF'!$A$2:$C$14,3,FALSE) -> 0.03
A24: Martwe drewno | B24: tourism=information | C24: 50.845504 | D24: 20.569926 | E24: infrastruktura;; | G24: =VLOOKUP(B24,'Category-INF'!$A$2:$C$14,3,FALSE) -> 0
A25: Wrzosowy Bufet | B25: amenity=fast_food | C25: 50.845608 | D25: 20.641981 | E25: infrastruktura;; | G25: =VLOOKUP(B25,'Category-INF'!$A$2:$C$14,3,FALSE) -> 0.03
A26: Sushi World | B26: amenity=restaurant | C26: 50.846819 | D26: 20.626742 | E26: infrastruktura;; | G26: =VLOOKUP(B26,'Category-INF'!$A$2:$C$14,3,FALSE) -> 0.1
... A71: Piri Piri Pizza | B71: amenity=restaurant | C71: 50.862141 | D71: 20.624628 | E71: infrastruktura;; | G71: =VLOOKUP(B71,'Category-INF'!$A$2:$C$14,3,FALSE) -> 0.1
A72: Świętokrzyski szlak archeo-geologiczny | B72: tourism=information | C72: 50.862933 | D72: 20.617004 | E72: infrastruktura;; | F72: Q24941880 | G72: =VLOOKUP(B72,'Category-INF'!$A$2:$C$14,3,FALSE) -> 0
A73: Marmurowa | B73: amenity=restaurant | C73: 50.86306 | D73: 20.627223 | E73: infrastruktura;; | G73: =VLOOKUP(B73,'Category-INF'!$A$2:$C$14,3,FALSE) -> 0.1
A74: Fenomen | B74: amenity=cinema | C74: 50.863491 | D74: 20.626821 | E74: eventowa; kulturowa; | G74: =VLOOKUP(B74,'Category-INF'!$A$2:$C$14,3,FALSE) -> 0.1
A75: Willa Hueta | B75: tourism=hotel | C75: 50.86379 | D75: 20.631395 | E75: infrastruktura;; | G75: =VLOOKUP(B75,'Category-INF'!$A$2:$C$14,3,FALSE) -> 0.2
A76: Spektrum Smaku | B76: amenity=restaurant | C76: 50.863853 | D76: 20.631423 | E76: infrastruktura;; | G76: =VLOOKUP(B76,'Category-INF'!$A$2:$C$14,3,FALSE) -> 0.1
A77: Brak nazwy | B77: amenity=fountain | C77: 50.864137 | D77: 20.642249 | E77: infrastruktura;; | G77: =VLOOKUP(B77,'Category-INF'!$A$2:$C$14,3,FALSE) -> 0.01
A78: Schronisko PTSM Wędrownik | B78: tourism=hostel | C78: 50.864267 | D78: 20.648988 | E78: infrastruktura;; | G78: =VLOOKUP(B78,'Category-INF'!$A$2:$C$14,3,FALSE) -> 0.08
A79: Sushiba | B79: amenity=fast_food | C79: 50.864464 | D79: 20.637418 | E79: infrastruktura;; | G79: =VLOOKUP(B79,'Category-INF'!$A$2:$C$14,3,FALSE) -> 0.03
A80: Locombia - Smaki Kolumbii | B80: amenity=restaurant | C80: 50.864491 | D80: 20.637305 | E80: infrastruktura;; | G80: =VLOOKUP(B80,'Category-INF'!$A$2:$C$14,3,FALSE) -> 0.1
A81: Kebab Bites | B81: amenity=fast_food | C81: 50.864879 | D81: 20.637512 | E81: infrastruktura;; | G81: =VLOOKUP(B81,'Category-INF'!$A$2:$C$14,3,FALSE) -> 0.03
A82: Bar CBM | B82: amenity=fast_food | C82: 50.864897 | D82: 20.649671 | E82: infrastruktura;; | G82: =VLOOKUP(B82,'Category-INF'!$A$2:$C$14,3,FALSE) -> 0.03
A83: Green Diet Bufet | B83: amenity=restaurant | C83: 50.864988 | D83: 20.629734 | E83: infrastruktura;; | G83: =VLOOKUP(B83,'Category-INF'!$A$2:$C$14,3,FALSE) -> 0.1
A84: Yes Tu | B84: amenity=restaurant | C84: 50.865023 | D84: 20.649679 | E84: infrastruktura;; | G84: =VLOOKUP(B84,'Category-INF'!$A$2:$C$14,3,FALSE) -> 0.1
... A335: Brak nazwy | B335: amenity=fountain | C335: 50.873105 | D335: 20.632514 | E335: infrastruktura;; | G335: =VLOOKUP(B335,'Category-INF'!$A$2:$C$14,3,FALSE) -> 0.01
A336: Dal | B336: tourism=hotel | C336: 50.873116 | D336: 20.629497 | E336: infrastruktura;; | F336: Q112000599 | G336: =VLOOKUP(B336,'Category-INF'!$A$2:$C$14,3,FALSE) -> 0.2
A337: UNO pizza napoletana | B337: amenity=restaurant | C337: 50.873134 | D337: 20.632836 | E337: infrastruktura;; | G337: =VLOOKUP(B337,'Category-INF'!$A$2:$C$14,3,FALSE) -> 0.1
A338: Cukiernia Świat Słodyczy | B338: amenity=cafe | C338: 50.873144 | D338: 20.624685 | E338: infrastruktura;; | G338: =VLOOKUP(B338,'Category-INF'!$A$2:$C$14,3,FALSE) -> 0.05
A339: Flower Bar | B339: amenity=cafe | C339: 50.873227 | D339: 20.629398 | E339: infrastruktura;; | G339: =VLOOKUP(B339,'Category-INF'!$A$2:$C$14,3,FALSE) -> 0.05
A340: DAL Hotel | B340: tourism=hotel | C340: 50.873332 | D340: 20.629464 | E340: infrastruktura;; | G340: =VLOOKUP(B340,'Category-INF'!$A$2:$C$14,3,FALSE) -> 0.2
A341: La Baguette | B341: amenity=cafe | C341: 50.873369 | D341: 20.630722 | E341: infrastruktura;; | G341: =VLOOKUP(B341,'Category-INF'!$A$2:$C$14,3,FALSE) -> 0.05
A342: Selfie Spicy | B342: amenity=fast_food | C342: 50.873418 | D342: 20.62043 | E342: infrastruktura;; | G342: =VLOOKUP(B342,'Category-INF'!$A$2:$C$14,3,FALSE) -> 0.03
A343: Fit Cake | B343: amenity=cafe | C343: 50.873425 | D343: 20.628746 | E343: infrastruktura;; | G343: =VLOOKUP(B343,'Category-INF'!$A$2:$C$14,3,FALSE) -> 0.05
A344: Bar Turystyczny | B344: amenity=fast_food | C344: 50.873489 | D344: 20.619449 | E344: infrastruktura;; | G344: =VLOOKUP(B344,'Category-INF'!$A$2:$C$14,3,FALSE) -> 0.03
A345: Ferment | B345: amenity=restaurant | C345: 50.873584 | D345: 20.621084 | E345: infrastruktura;; | G345: =VLOOKUP(B345,'Category-INF'!$A$2:$C$14,3,FALSE) -> 0.1
A346: Stara Piekarnia | B346: amenity=restaurant | C346: 50.873585 | D346: 20.628206 | E346: infrastruktura;; | G346: =VLOOKUP(B346,'Category-INF'!$A$2:$C$14,3,FALSE) -> 0.1
A347: Galata Kebab & Tantuni | B347: amenity=fast_food | C347: 50.873587 | D347: 20.632585 | E347: infrastruktura;; | G347: =VLOOKUP(B347,'Category-INF'!$A$2:$C$14,3,FALSE) -> 0.03
A348: Jadłodalnia Tempo | B348: amenity=restaurant | C348: 50.873621 | D348: 20.623729 | E348: infrastruktura;; | G348: =VLOOKUP(B348,'Category-INF'!$A$2:$C$14,3,FALSE) -> 0.1
... A545: Tarnów / Kielce / Centrum | B545: tourism=information | C545: 50.913058 | D545: 20.680943 | E545: infrastruktura;; | G545: =VLOOKUP(B545,'Category-INF'!$A$2:$C$14,3,FALSE) -> 0

Sheet Category - BG
A1: KATEGORIA | B1: LICZBA | C1: WAGI | D1: WYJAŚNIENIE
A2: amenity=parking | B2: 3906 | C2: 0 | D2: Parking
A3: amenity=bench | B3: 2538 | C3: 0 | D3: Ławeczka
A4: amenity=parking_space | B4: 1515 | C4: 0 | D4: Miejse parkingowe (dla niepełnosprawnych, stacja ładowania)
A5: amenity=waste_basket | B5: 1097 | C5: 0 | D5: Koszt na śmieci
A6: public_transport=platform | B6: 721 | C6: 0 | D6: Przystanek
A7: public_transport=stop_position | B7: 578 | C7: 0 | D7: Miejsce zatrzymywania
A8: highway=platform | B8: 460 | C8: 0 | D8: Przystanek
A9: amenity=shelter | B9: 430 | C9: 0 | D9: Wiata (przystankowa)
A10: amenity=waste_disposal | B10: 311 | C10: 0 | D10: Śmietnik, kontenery na odpady
A11: shop=clothes | B11: 272 | C11: 0.01 | D11: Sklep odziezowy
A12: amenity=parcel_locker | B12: 223 | C12: 0 | D12: Paczkomat
A13: shop=convenience | B13: 221 | C13: 0 | D13: Sklep spożywczy (osiedlowy)
... A30: office=government | B30: 63 | C30: 0.02 | D30: Urząd rządowy / administracja publiczna
A31: amenity=bicycle_rental | B31: 62 | D31: Wypożyczalnia rowerów | G31: Do infrastruktury ?
A32: leisure=fitness_station | B32: 58 | D32: Siłownia plenerowa (pod chmurką)
A33: office=insurance | B33: 57 | C33: Y | D33: Agencja ubezpieczeniowa
A34: amenity=car_wash | B34: 56 | C34: Y | D34: Myjnia samochodowa
A35: amenity=clinic | B35: 55 | C35: Y | D35: Przychodnia / ambulatoryjna klinika
A36: shop=butcher | B36: 54 | D36: Sklep mięsny
A37: shop=optician | B37: 48 | D37: Optyk
A38: shop=jewelry | B38: 47 | D38: Jubiler
A39: amenity=bank | B39: 46 | D39: Bank
A40: shop=car_parts | B40: 44 | D40: Sklep z częściami samochodowymi
A41: shop=shoes | B41: 44 | D41: Sklep z butami
A42: shop=florist | B42: 43 | D42: Kwiaciarnia
A43: leisure=track | B43: 39 | D43: Bieżnia / tor sportowy (np. lekkoatletyczny, gokartowy)
A44: shop=greengrocer | B44: 39 | D44: Warzywniak / sklep z warzywami i owocami
A45: amenity=toilets | B45: 37 | D45: Publiczna toaleta
A46: amenity=post_office | B46: 36 | D46: Poczta (placówka)
A47: office=accountant | B47: 36 | D47: Biuro rachunkowe / księgowość
... A51: amenity=fuel | B51: 32 | D51: Stacja paliw
A52: amenity=university | B52: 32 | C52: Y | D52: Uniwersytet / uczelnia wyższa
A53: office=religion | B53: 32 | D53: Biuro parafialne / administracja związku wyznaniowego
A54: shop=electronics | B54: 32 | D54: Sklep ze sprzętem RTV/AGD
A55: shop=furniture | B55: 29 | D55: Sklep meblowy
A56: shop=wholesale | B56: 29 | D56: Hurtownia
A57: amenity=bureau_de_change | B57: 27 | D57: Kantor wymiany walut
A58: shop=tailor | B58: 27 | D58: Krawiec
A59: amenity=trolley_bay | B59: 26 | D59: Wiata na wózki sklepowe
A60: shop=alcohol | B60: 26 | D60: Sklep monopolowy
A61: shop=car | B61: 26 | D61: Salon samochodowy (sprzedaż aut)
A62: shop=computer | B62: 26 | D62: Sklep komputerowy
A63: amenity=ice_cream | B63: 25 | D63: Lodziarnia
A64: amenity=lounger | B64: 25 | D64: Publiczny leżak miejski
... A83: amenity=language_school | B83: 18 | D83: Szkoła językowa
A84: amenity=library | B84: 18 | C84: 0.01 | D84: Biblioteka
A85: shop=books | B85: 18 | D85: Księgarnia
A86: shop=doors | B86: 18 | D86: Sklep z drzwiami (i oknami)
A87: shop=photo | B87: 18 | D87: Fotograf (studio i wywoływanie zdjęć)
A88: healthcare=laboratory | B88: 17 | D88: Laboratorium medyczne (analizy krwi itp.)
A89: leisure=picnic_table | B89: 17 | D89: Stół piknikowy
A90: shop=bicycle | B90: 17 | D90: Sklep rowerowy
A91: shop=massage | B91: 17 | C91: 0.02 | D91: Salon masażu
A92: amenity=veterinary | B92: 16 | C92: 0.02 | D92: Weterynarz
A93: highway=elevator | B93: 15 | D93: Winda
A94: shop=doityourself | B94: 15 | C94: 0.02 | D94: Market budowlany (typu Castorama, Leroy Merlin)
A95: historic=wayside_cross | B95: 14 | D95: Krzyż przydrożny
A96: leisure=bleachers | B96: 14 | D96: Trybuny (zazwyczaj niezadaszone, np. przy boisku szkolnym)
A97: office=advertising_agency | B97: 14 | D97: Agencja reklamowa
A98: shop=curtain | B98: 14 | D98: Sklep z firanami i zasłonami
A99: shop=interior_decoration | B99: 14 | D99: Sklep z dekoracjami wnętrz
A100: shop=mall | B100: 14 | C100: 0.03 | D100: Galeria handlowa / centrum handlowe
A101: shop=stationery | B101: 14 | D101: Sklep papierniczy
A102: amenity=community_centre | B102: 13 | D102: Dom kultury / świetlica wiejska / centrum społecznościowe
A103: shop=cosmetics | B103: 13 | D103: Sklep z kosmetykami
A104: shop=pet_grooming | B104: 13 | D104: Fryzjer dla psów i kotów (groomer)
A105: amenity=charging_station | B105: 12 | C105: 0.01 | D105: Stacja ładowania pojazdów elektrycznych
A106: amenity=compressed_air | B106: 12 | D106: Kompresor (np. na stacji paliw do pompowania opon)
A107: amenity=vehicle_inspection | B107: 12 | D107: Stacja kontroli pojazdów (przeglądy rejestracyjne)
A108: shop=hardware | B108: 12 | D108: Sklep żelazny / z narzędziami
A109: shop=tattoo | B109: 12 | D109: Studio tatuażu
A110: shop=toys | B110: 12 | D110: Sklep z zabawkami
A111: amenity=pub | B111: 11 | D111: Pub | G111: Do infrastruktury ?
A112: amenity=social_facility | B112: 11 | D112: Placówka opieki społecznej (np. noclegownia, DPS)
A113: office=association | B113: 11 | D113: Siedziba stowarzyszenia
A114: office=property_management | B114: 11 | D114: Zarządca nieruchomości / spółdzielnia mieszkaniowa
A115: shop=herbalist | B115: 11 | D115: Sklep zielarski
A116: amenity=loading_dock | B116: 10 | D116: Rampa rozładunkowa
A117: amenity=police | B117: 10 | D117: Policja / komisariat
A118: shop=copyshop | B118: 10 | D118: Ksero / punkt kserograficzny
A119: shop=funeral_directors | B119: 10 | D119: Zakład pogrzebowy
A120: shop=lighting | B120: 10 | D120: Sklep z oświetleniem / lampami
A121: shop=pawnbroker | B121: 10 | D121: Lombard
A122: shop=ticket | B122: 10 | D122: Kasa biletowa (kino, teatr, komunikacja)
A123: leisure=firepit | B123: 9 | D123: Wyznaczone miejsce na ognisko
... A125: shop=dry_cleaning | B125: 9 | D125: Pralnia chemiczna
A126: amenity=bar | B126: 8 | D126: Bar | G126: Do infrastruktury ?
A127: amenity=childcare | B127: 8 | D127: Opieka nad dziećmi (np. żłobek, klub dziecięcy)
A128: amenity=hospital | B128: 8 | C128: Y | D128: Szpital
A129: healthcare=sample_collection | B129: 8 | D129: Punkt pobrań (np. krwi, materiału do badań)
A130: leisure=tanning_salon | B130: 8 | C130: Y | D130: Solarium
A131: office=notary | B131: 8 | D131: Kancelaria notarialna (Notariusz)
A132: shop=fishing | B132: 8 | D132: Sklep wędkarski
A133: shop=paint | B133: 8 | D133: Sklep z farbami i lakierami
A134: shop=tobacco | B134: 8 | D134: Trafika / sklep z wyrobami tytoniowymi
A135: shop=trade | B135: 8 | C135: Y | D135: Hurtownia budowlana / instalacyjna (dla profesjonalistów)
A136: shop=window_blind | B136: 8 | D136: Sklep z roletami, żaluzjami i moskitierami
A137: amenity=drinking_water | B137: 7 | D137: Punkt z wodą pitną (np. poidełko miejskie)
A138: historic=building | B138: 7 | D138: Budynek zabytkowy
...

Sheet BG
A1: name | B1: category | C1: lat | D1: lon | E1: classification;;
A2: „Pawilony przy Wiśniowej” | B2: shop=department_store | C2: 50.885734 | D2: 20.637207 | E2: way
A3: 110 Hz audio showroom | B3: shop=hifi | C3: 50.861748 | D3: 20.62409 | E3: node
A4: 18stka | B4: amenity=bar | C4: 50.860164 | D4: 20.590833 | E4: node
A5: 2BRICK studio | B5: office=architect | C5: 50.846871 | D5: 20.626765 | E5: node
A6: 36 minut | B6: leisure=fitness_centre | C6: 50.885389 | D6: 20.629315 | E6: node
A7: 4F | B7: shop=clothes | C7: 50.882476 | D7: 20.58301 | E7: node
A8: 4F | B8: shop=clothes | C8: 50.875441 | D8: 20.635353 | E8: node
A9: 4F | B9: shop=clothes | C9: 50.879425 | D9: 20.646699 | E9: node
A10: 4PLN | B10: shop=variety_store | C10: 50.871076 | D10: 20.626171 | E10: node
A11: 50 Style | B11: shop=clothes | C11: 50.871149 | D11: 20.626158 | E11: node
A12: 77 Barber Shop | B12: shop=hairdresser | C12: 50.884151 | D12: 20.583244 | E12: node
A13: A & E | B13: shop=beauty | C13: 50.869711 | D13: 20.648727 | E13: node
... A5624: Medical | B5624: shop=medical_supply | C5624: 50.87352 | D5624: 20.597065 | E5624: node
